pygeneactiv/__init__.py
pygeneactiv/__version__.py
pygeneactiv/reader/__init__.py
pygeneactiv-0.2.dist-info/LICENSE
pygeneactiv-0.2.dist-info/METADATA
pygeneactiv-0.2.dist-info/WHEEL
pygeneactiv-0.2.dist-info/top_level.txt
pygeneactiv-0.2.dist-info/RECORD
